{
    "Total distance:": 1541.0101048468018,
    "Feasible?": true,
    "Battery feasible?": true,
    "All customers visited?": true,
    "Routes:": [
        {
            "Distance:": 68.2101844956272,
            "Feasible": true,
            "Battery feasible?": true,
            "Visits:": [
                {
                    "Location:": 0,
                    "Arrival time:": 0,
                    "Charged quantity:": 0
                },
                {
                    "Location:": 41,
                    "Arrival time:": 10.0,
                    "Charged quantity:": 0
                },
                {
                    "Location:": 43,
                    "Arrival time:": 102.82842712474618,
                    "Charged quantity:": 0
                },
                {
                    "Location:": 46,
                    "Arrival time:": 195.82842712474618,
                    "Charged quantity:": 0
                },
                {
                    "Location:": 48,
                    "Arrival time:": 287.8284271247462,
                    "Charged quantity:": 0
                },
                {
                    "Location:": 51,
                    "Arrival time:": 382.0710678118655,
                    "Charged quantity:": 0
                },
                {
                    "Location:": 49,
                    "Arrival time:": 475.0710678118655,
                    "Charged quantity:": 0
                },
                {
                    "Location:": 47,
                    "Arrival time:": 567.0710678118655,
                    "Charged quantity:": 0
                },
                {
                    "Location:": 31,
                    "Arrival time:": 776.8660687473185,
                    "Charged quantity:": 0
                },
                {
                    "Location:": 32,
                    "Arrival time:": 872.0,
                    "Charged quantity:": 0
                },
                {
                    "Location:": 30,
                    "Arrival time:": 965.1622776601683,
                    "Charged quantity:": 0
                },
                {
                    "Location:": 29,
                    "Arrival time:": 1057.1622776601685,
                    "Charged quantity:": 0
                },
                {
                    "Location:": 0,
                    "Arrival time:": 1165.2730479364434,
                    "Charged quantity:": 0
                }
            ]
        },
        {
            "Distance:": 89.89016321906435,
            "Feasible": true,
            "Battery feasible?": true,
            "Visits:": [
                {
                    "Location:": 0,
                    "Arrival time:": 0,
                    "Charged quantity:": 0.0
                },
                {
                    "Location:": 42,
                    "Arrival time:": 10.198039027185569,
                    "Charged quantity:": 0
                },
                {
                    "Location:": 45,
                    "Arrival time:": 106.3851648071345,
                    "Charged quantity:": 0
                },
                {
                    "Location:": 50,
                    "Arrival time:": 201.38516480713452,
                    "Charged quantity:": 0
                },
                {
                    "Location:": 65,
                    "Arrival time:": 314.7089723865157,
                    "Charged quantity:": 0
                },
                {
                    "Location:": 66,
                    "Arrival time:": 417.0,
                    "Charged quantity:": 0
                },
                {
                    "Location:": 69,
                    "Arrival time:": 513.0,
                    "Charged quantity:": 0
                },
                {
                    "Location:": 67,
                    "Arrival time:": 605.8284271247462,
                    "Charged quantity:": 0
                },
                {
                    "Location:": 68,
                    "Arrival time:": 698.8284271247462,
                    "Charged quantity:": 0
                },
                {
                    "Location:": 64,
                    "Arrival time:": 791.8284271247462,
                    "Charged quantity:": 0
                },
                {
                    "Location:": 71,
                    "Arrival time:": 889.4442002306101,
                    "Charged quantity:": 0
                },
                {
                    "Location:": 70,
                    "Arrival time:": 1016.605551275464,
                    "Charged quantity:": 0
                },
                {
                    "Location:": 14,
                    "Arrival time:": 1109.4339784002102,
                    "Charged quantity:": 10.20016321906435
                },
                {
                    "Location:": 0,
                    "Arrival time:": 1163.117504887381,
                    "Charged quantity:": 0
                }
            ]
        },
        {
            "Distance:": 108.61051288964592,
            "Feasible": true,
            "Battery feasible?": true,
            "Visits:": [
                {
                    "Location:": 0,
                    "Arrival time:": 0,
                    "Charged quantity:": 0.0
                },
                {
                    "Location:": 88,
                    "Arrival time:": 12.206555615733702,
                    "Charged quantity:": 0
                },
                {
                    "Location:": 86,
                    "Arrival time:": 104.0,
                    "Charged quantity:": 0
                },
                {
                    "Location:": 83,
                    "Arrival time:": 199.38516480713452,
                    "Charged quantity:": 0
                },
                {
                    "Location:": 85,
                    "Arrival time:": 294.77032961426903,
                    "Charged quantity:": 0
                },
                {
                    "Location:": 89,
                    "Arrival time:": 387.77032961426903,
                    "Charged quantity:": 0
                },
                {
                    "Location:": 90,
                    "Arrival time:": 482.77032961426903,
                    "Charged quantity:": 0
                },
                {
                    "Location:": 16,
                    "Arrival time:": 579.981432165197,
                    "Charged quantity:": 28.92051288964592
                },
                {
                    "Location:": 75,
                    "Arrival time:": 699.235174296693,
                    "Charged quantity:": 0
                },
                {
                    "Location:": 93,
                    "Arrival time:": 922.8254244210267,
                    "Charged quantity:": 0
                },
                {
                    "Location:": 82,
                    "Arrival time:": 1015.8254244210267,
                    "Charged quantity:": 0
                },
                {
                    "Location:": 87,
                    "Arrival time:": 1111.656376315872,
                    "Charged quantity:": 0
                },
                {
                    "Location:": 0,
                    "Arrival time:": 1218.209321673119,
                    "Charged quantity:": 0
                }
            ]
        },
        {
            "Distance:": 120.50322238657088,
            "Feasible": true,
            "Battery feasible?": true,
            "Visits:": [
                {
                    "Location:": 0,
                    "Arrival time:": 0,
                    "Charged quantity:": 0.0
                },
                {
                    "Location:": 44,
                    "Arrival time:": 13.0,
                    "Charged quantity:": 0
                },
                {
                    "Location:": 22,
                    "Arrival time:": 124.40093455903269,
                    "Charged quantity:": 0
                },
                {
                    "Location:": 119,
                    "Arrival time:": 229.1657576192661,
                    "Charged quantity:": 0
                },
                {
                    "Location:": 4,
                    "Arrival time:": 324.16575761926606,
                    "Charged quantity:": 40.813222386570885
                },
                {
                    "Location:": 23,
                    "Arrival time:": 475.9762055568151,
                    "Charged quantity:": 0
                },
                {
                    "Location:": 25,
                    "Arrival time:": 592.605551275464,
                    "Charged quantity:": 0
                },
                {
                    "Location:": 27,
                    "Arrival time:": 684.8416192529638,
                    "Charged quantity:": 0
                },
                {
                    "Location:": 28,
                    "Arrival time:": 777.8416192529638,
                    "Charged quantity:": 0
                },
                {
                    "Location:": 24,
                    "Arrival time:": 869.8416192529638,
                    "Charged quantity:": 0
                },
                {
                    "Location:": 26,
                    "Arrival time:": 960.8416192529638,
                    "Charged quantity:": 0
                },
                {
                    "Location:": 112,
                    "Arrival time:": 1069.5231609452333,
                    "Charged quantity:": 0
                },
                {
                    "Location:": 0,
                    "Arrival time:": 1181.883840720231,
                    "Charged quantity:": 0
                }
            ]
        },
        {
            "Distance:": 115.2134459695157,
            "Feasible": true,
            "Battery feasible?": true,
            "Visits:": [
                {
                    "Location:": 0,
                    "Arrival time:": 0,
                    "Charged quantity:": 0.0
                },
                {
                    "Location:": 84,
                    "Arrival time:": 14.142135623730951,
                    "Charged quantity:": 0
                },
                {
                    "Location:": 95,
                    "Arrival time:": 110.8309518948453,
                    "Charged quantity:": 0
                },
                {
                    "Location:": 63,
                    "Arrival time:": 221.054700311002,
                    "Charged quantity:": 0
                },
                {
                    "Location:": 54,
                    "Arrival time:": 355.24880949681335,
                    "Charged quantity:": 0
                },
                {
                    "Location:": 52,
                    "Arrival time:": 450.63397430394787,
                    "Charged quantity:": 0
                },
                {
                    "Location:": 12,
                    "Arrival time:": 562.0,
                    "Charged quantity:": 26.956460958608062
                },
                {
                    "Location:": 72,
                    "Arrival time:": 665.4239972284737,
                    "Charged quantity:": 0
                },
                {
                    "Location:": 73,
                    "Arrival time:": 918.0,
                    "Charged quantity:": 0
                },
                {
                    "Location:": 14,
                    "Arrival time:": 1134.2360679774997,
                    "Charged quantity:": 8.566985010907644
                },
                {
                    "Location:": 0,
                    "Arrival time:": 1182.3831203390193,
                    "Charged quantity:": 0
                }
            ]
        },
        {
            "Distance:": 108.15692790011984,
            "Feasible": true,
            "Battery feasible?": true,
            "Visits:": [
                {
                    "Location:": 0,
                    "Arrival time:": 0,
                    "Charged quantity:": 0.0
                },
                {
                    "Location:": 96,
                    "Arrival time:": 15.811388300841896,
                    "Charged quantity:": 0
                },
                {
                    "Location:": 108,
                    "Arrival time:": 128.3606797749979,
                    "Charged quantity:": 0
                },
                {
                    "Location:": 107,
                    "Arrival time:": 219.3606797749979,
                    "Charged quantity:": 0
                },
                {
                    "Location:": 103,
                    "Arrival time:": 318.3606797749979,
                    "Charged quantity:": 0
                },
                {
                    "Location:": 104,
                    "Arrival time:": 552.0,
                    "Charged quantity:": 0
                },
                {
                    "Location:": 105,
                    "Arrival time:": 649.605551275464,
                    "Charged quantity:": 0
                },
                {
                    "Location:": 106,
                    "Arrival time:": 742.8284271247462,
                    "Charged quantity:": 0
                },
                {
                    "Location:": 109,
                    "Arrival time:": 835.8284271247462,
                    "Charged quantity:": 0
                },
                {
                    "Location:": 110,
                    "Arrival time:": 929.8284271247462,
                    "Charged quantity:": 0
                },
                {
                    "Location:": 2,
                    "Arrival time:": 1031.4903309144368,
                    "Charged quantity:": 28.466927900119842
                },
                {
                    "Location:": 0,
                    "Arrival time:": 1161.053767005476,
                    "Charged quantity:": 0
                }
            ]
        },
        {
            "Distance:": 103.34062055047556,
            "Feasible": true,
            "Battery feasible?": true,
            "Visits:": [
                {
                    "Location:": 0,
                    "Arrival time:": 0,
                    "Charged quantity:": 0.0
                },
                {
                    "Location:": 62,
                    "Arrival time:": 18.681541692269406,
                    "Charged quantity:": 0
                },
                {
                    "Location:": 61,
                    "Arrival time:": 141.0,
                    "Charged quantity:": 0
                },
                {
                    "Location:": 79,
                    "Arrival time:": 258.17935662402834,
                    "Charged quantity:": 0
                },
                {
                    "Location:": 77,
                    "Arrival time:": 350.17935662402834,
                    "Charged quantity:": 0
                },
                {
                    "Location:": 74,
                    "Arrival time:": 444.17935662402834,
                    "Charged quantity:": 0
                },
                {
                    "Location:": 17,
                    "Arrival time:": 541.3904591749563,
                    "Charged quantity:": 8.224166074670393
                },
                {
                    "Location:": 76,
                    "Arrival time:": 576.4814847190169,
                    "Charged quantity:": 0
                },
                {
                    "Location:": 78,
                    "Arrival time:": 997.0,
                    "Charged quantity:": 0
                },
                {
                    "Location:": 16,
                    "Arrival time:": 1103.0312195418815,
                    "Charged quantity:": 15.426454475805173
                },
                {
                    "Location:": 0,
                    "Arrival time:": 1174.3531978053015,
                    "Charged quantity:": 0
                }
            ]
        },
        {
            "Distance:": 105.47628611364532,
            "Feasible": true,
            "Battery feasible?": true,
            "Visits:": [
                {
                    "Location:": 0,
                    "Arrival time:": 0,
                    "Charged quantity:": 0.0
                },
                {
                    "Location:": 111,
                    "Arrival time:": 20.615528128088304,
                    "Charged quantity:": 0
                },
                {
                    "Location:": 117,
                    "Arrival time:": 136.0,
                    "Charged quantity:": 0
                },
                {
                    "Location:": 116,
                    "Arrival time:": 269.0,
                    "Charged quantity:": 0
                },
                {
                    "Location:": 115,
                    "Arrival time:": 367.605551275464,
                    "Charged quantity:": 0
                },
                {
                    "Location:": 113,
                    "Arrival time:": 461.211102550928,
                    "Charged quantity:": 0
                },
                {
                    "Location:": 114,
                    "Arrival time:": 553.211102550928,
                    "Charged quantity:": 0
                },
                {
                    "Location:": 118,
                    "Arrival time:": 648.211102550928,
                    "Charged quantity:": 0
                },
                {
                    "Location:": 121,
                    "Arrival time:": 743.211102550928,
                    "Charged quantity:": 0
                },
                {
                    "Location:": 120,
                    "Arrival time:": 839.0,
                    "Charged quantity:": 0
                },
                {
                    "Location:": 4,
                    "Arrival time:": 930.0,
                    "Charged quantity:": 25.786286113645318
                },
                {
                    "Location:": 0,
                    "Arrival time:": 1050.0651653598866,
                    "Charged quantity:": 0
                }
            ]
        },
        {
            "Distance:": 111.21501647463843,
            "Feasible": true,
            "Battery feasible?": true,
            "Visits:": [
                {
                    "Location:": 0,
                    "Arrival time:": 0,
                    "Charged quantity:": 0.0
                },
                {
                    "Location:": 33,
                    "Arrival time:": 38.07886552931954,
                    "Charged quantity:": 0
                },
                {
                    "Location:": 35,
                    "Arrival time:": 269.0,
                    "Charged quantity:": 0
                },
                {
                    "Location:": 37,
                    "Arrival time:": 361.0,
                    "Charged quantity:": 0
                },
                {
                    "Location:": 40,
                    "Arrival time:": 458.0710678118655,
                    "Charged quantity:": 0
                },
                {
                    "Location:": 39,
                    "Arrival time:": 553.0710678118655,
                    "Charged quantity:": 0
                },
                {
                    "Location:": 38,
                    "Arrival time:": 650.0,
                    "Charged quantity:": 0
                },
                {
                    "Location:": 36,
                    "Arrival time:": 745.3851648071345,
                    "Charged quantity:": 0
                },
                {
                    "Location:": 8,
                    "Arrival time:": 838.3851648071345,
                    "Charged quantity:": 12.766491101293923
                },
                {
                    "Location:": 34,
                    "Arrival time:": 886.7625891541137,
                    "Charged quantity:": 0
                },
                {
                    "Location:": 8,
                    "Arrival time:": 1137.0990195135928,
                    "Charged quantity:": 18.75852537334451
                },
                {
                    "Location:": 0,
                    "Arrival time:": 1235.1722998283642,
                    "Charged quantity:": 0
                }
            ]
        },
        {
            "Distance:": 104.15179221870035,
            "Feasible": true,
            "Battery feasible?": true,
            "Visits:": [
                {
                    "Location:": 0,
                    "Arrival time:": 0,
                    "Charged quantity:": 0.0
                },
                {
                    "Location:": 55,
                    "Arrival time:": 32.38826948140329,
                    "Charged quantity:": 0
                },
                {
                    "Location:": 53,
                    "Arrival time:": 289.3851648071345,
                    "Charged quantity:": 0
                },
                {
                    "Location:": 60,
                    "Arrival time:": 390.5655046946335,
                    "Charged quantity:": 0
                },
                {
                    "Location:": 59,
                    "Arrival time:": 485.5655046946335,
                    "Charged quantity:": 0
                },
                {
                    "Location:": 58,
                    "Arrival time:": 577.5655046946335,
                    "Charged quantity:": 0
                },
                {
                    "Location:": 56,
                    "Arrival time:": 673.3964565894788,
                    "Charged quantity:": 0
                },
                {
                    "Location:": 12,
                    "Arrival time:": 772.340728499478,
                    "Charged quantity:": 8.347409751045475
                },
                {
                    "Location:": 14,
                    "Arrival time:": 814.9562686187985,
                    "Charged quantity:": 16.114382467654877
                },
                {
                    "Location:": 0,
                    "Arrival time:": 888.6889983586914,
                    "Charged quantity:": 0
                }
            ]
        },
        {
            "Distance:": 90.82959326119902,
            "Feasible": true,
            "Battery feasible?": true,
            "Visits:": [
                {
                    "Location:": 0,
                    "Arrival time:": 0,
                    "Charged quantity:": 0.0
                },
                {
                    "Location:": 80,
                    "Arrival time:": 35.05709628591621,
                    "Charged quantity:": 0
                },
                {
                    "Location:": 81,
                    "Arrival time:": 166.44030650891054,
                    "Charged quantity:": 0
                },
                {
                    "Location:": 16,
                    "Arrival time:": 283.3058928759318,
                    "Charged quantity:": 11.139593261199025
                },
                {
                    "Location:": 0,
                    "Arrival time:": 340.09541162183694,
                    "Charged quantity:": 0
                }
            ]
        },
        {
            "Distance:": 172.732316164989,
            "Feasible": true,
            "Battery feasible?": true,
            "Visits:": [
                {
                    "Location:": 0,
                    "Arrival time:": 0,
                    "Charged quantity:": 0.0
                },
                {
                    "Location:": 57,
                    "Arrival time:": 35.35533905932738,
                    "Charged quantity:": 0
                },
                {
                    "Location:": 14,
                    "Arrival time:": 390.4722050542442,
                    "Charged quantity:": 57.827544113571605
                },
                {
                    "Location:": 99,
                    "Arrival time:": 648.5398292763354,
                    "Charged quantity:": 0
                },
                {
                    "Location:": 102,
                    "Arrival time:": 760.0,
                    "Charged quantity:": 0
                },
                {
                    "Location:": 20,
                    "Arrival time:": 862.4017542509914,
                    "Charged quantity:": 35.214772051417384
                },
                {
                    "Location:": 0,
                    "Arrival time:": 1020.2505996286391,
                    "Charged quantity:": 0
                }
            ]
        },
        {
            "Distance:": 125.9216632282108,
            "Feasible": true,
            "Battery feasible?": true,
            "Visits:": [
                {
                    "Location:": 0,
                    "Arrival time:": 0,
                    "Charged quantity:": 0.0
                },
                {
                    "Location:": 20,
                    "Arrival time:": 38.47076812334269,
                    "Charged quantity:": 14.682827451139229
                },
                {
                    "Location:": 94,
                    "Arrival time:": 106.3563234589795,
                    "Charged quantity:": 0
                },
                {
                    "Location:": 91,
                    "Arrival time:": 380.0,
                    "Charged quantity:": 0
                },
                {
                    "Location:": 100,
                    "Arrival time:": 488.0,
                    "Charged quantity:": 0
                },
                {
                    "Location:": 98,
                    "Arrival time:": 579.0,
                    "Charged quantity:": 0
                },
                {
                    "Location:": 101,
                    "Arrival time:": 674.8309518948453,
                    "Charged quantity:": 0
                },
                {
                    "Location:": 20,
                    "Arrival time:": 777.8693567052505,
                    "Charged quantity:": 31.548835777071574
                },
                {
                    "Location:": 0,
                    "Arrival time:": 923.290678112866,
                    "Charged quantity:": 0
                }
            ]
        },
        {
            "Distance:": 116.75835997439928,
            "Feasible": true,
            "Battery feasible?": true,
            "Visits:": [
                {
                    "Location:": 0,
                    "Arrival time:": 0,
                    "Charged quantity:": 0.0
                },
                {
                    "Location:": 92,
                    "Arrival time:": 57.0087712549569,
                    "Charged quantity:": 0
                },
                {
                    "Location:": 97,
                    "Arrival time:": 576.0,
                    "Charged quantity:": 0
                },
                {
                    "Location:": 20,
                    "Arrival time:": 682.2788205960996,
                    "Charged quantity:": 37.068359974399286
                },
                {
                    "Location:": 0,
                    "Arrival time:": 846.411329032656,
                    "Charged quantity:": 0
                }
            ]
        }
    ]
}