{
    "Total distance:": 417.04466964751174,
    "Feasible?": true,
    "Battery feasible?": true,
    "All customers visited?": true,
    "Time to obtain:": 0.0,
    "Routes:": [
        {
            "Distance:": 94.38715253599001,
            "Feasible": true,
            "Battery feasible?": true,
            "Visits:": [
                {
                    "Location:": 0,
                    "Arrival time:": 0,
                    "Charged quantity:": 0.0
                },
                {
                    "Location:": 15,
                    "Arrival time:": 21.095023109728988,
                    "Charged quantity:": 0
                },
                {
                    "Location:": 19,
                    "Arrival time:": 67.43908891458577,
                    "Charged quantity:": 0
                },
                {
                    "Location:": 3,
                    "Arrival time:": 89.0,
                    "Charged quantity:": 25.02386967791736
                },
                {
                    "Location:": 9,
                    "Arrival time:": 114.3001009525848,
                    "Charged quantity:": 0
                },
                {
                    "Location:": 10,
                    "Arrival time:": 134.30010095258478,
                    "Charged quantity:": 0
                },
                {
                    "Location:": 1,
                    "Arrival time:": 163.16552506059645,
                    "Charged quantity:": 8.733282858072648
                },
                {
                    "Location:": 16,
                    "Arrival time:": 173.76938898138883,
                    "Charged quantity:": 0
                },
                {
                    "Location:": 0,
                    "Arrival time:": 199.32455532033677,
                    "Charged quantity:": 0
                }
            ]
        },
        {
            "Distance:": 92.21666436793775,
            "Feasible": true,
            "Battery feasible?": true,
            "Visits:": [
                {
                    "Location:": 0,
                    "Arrival time:": 0,
                    "Charged quantity:": 0.0
                },
                {
                    "Location:": 11,
                    "Arrival time:": 23.021728866442675,
                    "Charged quantity:": 0
                },
                {
                    "Location:": 4,
                    "Arrival time:": 98.0,
                    "Charged quantity:": 14.986804668587748
                },
                {
                    "Location:": 20,
                    "Arrival time:": 109.81567024260758,
                    "Charged quantity:": 0
                },
                {
                    "Location:": 14,
                    "Arrival time:": 151.6619037896906,
                    "Charged quantity:": 0
                },
                {
                    "Location:": 4,
                    "Arrival time:": 173.0,
                    "Charged quantity:": 16.599859699350002
                },
                {
                    "Location:": 8,
                    "Arrival time:": 196.0,
                    "Charged quantity:": 0
                },
                {
                    "Location:": 0,
                    "Arrival time:": 229.1948270094864,
                    "Charged quantity:": 0
                }
            ]
        },
        {
            "Distance:": 77.1707147685386,
            "Feasible": true,
            "Battery feasible?": true,
            "Visits:": [
                {
                    "Location:": 0,
                    "Arrival time:": 0,
                    "Charged quantity:": 0.0
                },
                {
                    "Location:": 18,
                    "Arrival time:": 26.248809496813376,
                    "Charged quantity:": 0
                },
                {
                    "Location:": 21,
                    "Arrival time:": 50.92838827718412,
                    "Charged quantity:": 0
                },
                {
                    "Location:": 4,
                    "Arrival time:": 104.88854381999832,
                    "Charged quantity:": 16.5407147685386
                },
                {
                    "Location:": 0,
                    "Arrival time:": 132.09846723112503,
                    "Charged quantity:": 0
                }
            ]
        },
        {
            "Distance:": 93.6044024143402,
            "Feasible": true,
            "Battery feasible?": true,
            "Visits:": [
                {
                    "Location:": 0,
                    "Arrival time:": 0,
                    "Charged quantity:": 0.0
                },
                {
                    "Location:": 13,
                    "Arrival time:": 29.206163733020468,
                    "Charged quantity:": 0
                },
                {
                    "Location:": 7,
                    "Arrival time:": 65.28010988928052,
                    "Charged quantity:": 0
                },
                {
                    "Location:": 5,
                    "Arrival time:": 101.47213595499957,
                    "Charged quantity:": 32.9744024143402
                },
                {
                    "Location:": 12,
                    "Arrival time:": 136.73456631256906,
                    "Charged quantity:": 0
                },
                {
                    "Location:": 0,
                    "Arrival time:": 199.54101966249684,
                    "Charged quantity:": 0
                }
            ]
        },
        {
            "Distance:": 59.665735560705194,
            "Feasible": true,
            "Battery feasible?": true,
            "Visits:": [
                {
                    "Location:": 0,
                    "Arrival time:": 0,
                    "Charged quantity:": 0
                },
                {
                    "Location:": 17,
                    "Arrival time:": 29.832867780352597,
                    "Charged quantity:": 0
                },
                {
                    "Location:": 0,
                    "Arrival time:": 146.8328677803526,
                    "Charged quantity:": 0
                }
            ]
        }
    ]
}